pdf2md/__init__.py
pdf2md/cli.py
pdf2md/core.py
pdf2md/exceptions.py
pdf2md/layout.py
pdf2md/markdownifier.py
pdf2md/ocr.py
pdf2md/renderer.py
pdf2md_converter-0.1.0.dist-info/licenses/LICENSE
pdf2md_converter-0.1.0.dist-info/METADATA
pdf2md_converter-0.1.0.dist-info/WHEEL
pdf2md_converter-0.1.0.dist-info/entry_points.txt
pdf2md_converter-0.1.0.dist-info/top_level.txt
pdf2md_converter-0.1.0.dist-info/RECORD
