Metadata-Version: 2.4
Name: pdf2md-converter
Version: 0.1.0
Summary: A PDF to clean, pagewise Markdown converter.
Author-email: Pratik <pratikpradhan64@gmail.com>
Classifier: Programming Language :: Python :: 3
Classifier: License :: OSI Approved :: MIT License
Classifier: Operating System :: OS Independent
Requires-Python: >=3.9
License-File: LICENSE
Requires-Dist: Pillow
Requires-Dist: PyMuPDF
Requires-Dist: torch
Requires-Dist: transformers
Requires-Dist: pytest
Requires-Dist: protobuf>=6.32.1
Requires-Dist: torchvision>=0.23.0
Requires-Dist: sentencepiece>=0.2.1
Requires-Dist: pytesseract>=0.3.13
Provides-Extra: all
Requires-Dist: easyocr; extra == "all"
Requires-Dist: pytesseract; extra == "all"
Requires-Dist: layoutparser[detectron2]; extra == "all"
Provides-Extra: test
Requires-Dist: pytest; extra == "test"
Requires-Dist: pytest-mock; extra == "test"
Requires-Dist: psutil; extra == "test"
Dynamic: license-file
